__init__.py
hello.py
fireflai-0.0.0.dist-info/METADATA
fireflai-0.0.0.dist-info/WHEEL
fireflai-0.0.0.dist-info/top_level.txt
fireflai-0.0.0.dist-info/RECORD
