Metadata-Version: 2.4
Name: fireflai
Version: 0.0.0
Summary: Add your description here
Requires-Python: >=3.12
Requires-Dist: twine>=6.2.0
